geomove/__init__.py
geomove/move.py
geomove-0.0.4.dist-info/LICENSE
geomove-0.0.4.dist-info/METADATA
geomove-0.0.4.dist-info/WHEEL
geomove-0.0.4.dist-info/top_level.txt
geomove-0.0.4.dist-info/RECORD
