Metadata-Version: 2.1
Name: geomove
Version: 0.0.4
Summary: Moves points on earth's surface towards a given bearing by a given distance.
Home-page: https://github.com/merschformann/geomove
Author: Marius Merschformann
Author-email: marius.merschformann@gmail.com
License: UNKNOWN
Platform: UNKNOWN
Classifier: Programming Language :: Python :: 3
Classifier: License :: OSI Approved :: MIT License
Classifier: Operating System :: OS Independent
Classifier: Topic :: Scientific/Engineering :: GIS
License-File: LICENSE
